binilla/CHANGELOG.MD
binilla/LICENSE.TXT
binilla/README.MD
binilla/__init__.py
binilla/__main__.py
binilla/app_window.py
binilla/constants.py
binilla/edit_manager.py
binilla/editor_constants.py
binilla/handler.py
binilla/run.py
binilla/util.py
binilla/defs/__init__.py
binilla/defs/config_def.py
binilla/defs/config_tooltips.py
binilla/defs/hotkey_enums.py
binilla/defs/style_def.py
binilla/defs/style_tooltips.py
binilla/defs/upgrade_config.py
binilla/defs/upgrade_style.py
binilla/defs/v1_config_def.py
binilla/defs/v1_style_def.py
binilla/styles/dark red.sty
binilla/styles/guerilla.sty
binilla/styles/light.sty
binilla/widgets/__init__.py
binilla/widgets/binilla_widget.py
binilla/widgets/bitmap_display_frame.py
binilla/widgets/field_widget_picker.py
binilla/widgets/font_config.py
binilla/widgets/scroll_menu.py
binilla/widgets/style_change_lock.py
binilla/widgets/tooltip_handler.py
binilla/widgets/field_widgets/__init__.py
binilla/widgets/field_widgets/array_frame.py
binilla/widgets/field_widgets/bool_frame.py
binilla/widgets/field_widgets/color_picker_frame.py
binilla/widgets/field_widgets/computed_text_frame.py
binilla/widgets/field_widgets/container_frame.py
binilla/widgets/field_widgets/data_frame.py
binilla/widgets/field_widgets/entry_frame.py
binilla/widgets/field_widgets/enum_frame.py
binilla/widgets/field_widgets/field_widget.py
binilla/widgets/field_widgets/simple_image_frame.py
binilla/widgets/field_widgets/stream_adapter_frame.py
binilla/widgets/field_widgets/text_frame.py
binilla/widgets/field_widgets/union_frame.py
binilla/windows/__init__.py
binilla/windows/about_window.py
binilla/windows/def_selector_window.py
binilla/windows/filedialog.py
binilla/windows/tag_window.py
binilla/windows/tag_window_manager.py
binilla-1.3.7.dist-info/LICENSE.TXT
binilla-1.3.7.dist-info/METADATA
binilla-1.3.7.dist-info/WHEEL
binilla-1.3.7.dist-info/top_level.txt
binilla-1.3.7.dist-info/RECORD
