Metadata-Version: 2.1
Name: binilla
Version: 1.3.7
Summary: A universal binary structure editor built on supyr_struct.
Home-page: https://github.com/Sigmmma/binilla
Author: Sigmmma
Author-email: MoeMakesStuff@gmail.com
License: MIT
Project-URL: Source, https://github.com/Sigmmma/binilla
Keywords: binilla,binary,data structure
Platform: POSIX
Platform: Windows
Classifier: Development Status :: 4 - Beta
Classifier: Intended Audience :: Developers
Classifier: Intended Audience :: End Users/Desktop
Classifier: License :: OSI Approved :: MIT License
Classifier: Programming Language :: Python
Classifier: Programming Language :: Python :: 3
Classifier: Programming Language :: Python :: 3.5
Classifier: Programming Language :: Python :: 3.6
Classifier: Programming Language :: Python :: 3.7
Classifier: Programming Language :: Python :: 3.8
Classifier: Programming Language :: Python :: 3.9
Classifier: Programming Language :: Python :: 3 :: Only
Requires: supyr_struct
Requires: threadsafe_tkinter
Requires: tkcolorpicker
Provides: binilla
Requires-Dist: supyr-struct
Requires-Dist: threadsafe-tkinter
Requires-Dist: tkcolorpicker
Provides-Extra: bitmap_viewing
Requires-Dist: arbytmap ; extra == 'bitmap_viewing'
